bumbo/__init__.py
bumbo/api.py
bumbo/middleware.py
bumbo/orm.py
bumbo/response.py
bumbo-0.0.14.dist-info/METADATA
bumbo-0.0.14.dist-info/WHEEL
bumbo-0.0.14.dist-info/top_level.txt
bumbo-0.0.14.dist-info/RECORD
